keras_utils/__init__.py
keras_utils/__init__.pyi
keras_utils/metrics.py
mr_keras_utils-0.1.1.dist-info/METADATA
mr_keras_utils-0.1.1.dist-info/WHEEL
mr_keras_utils-0.1.1.dist-info/top_level.txt
mr_keras_utils-0.1.1.dist-info/RECORD
