Metadata-Version: 2.1
Name: mr-keras-utils
Version: 0.1.1
Summary: Keras Utils, the Moveread way
Author-email: Marcel Claramunt <marcel@moveread.com>
Project-URL: repo, https://github.com/marciclabas/mltools.git
Requires-Python: >=3.10
Requires-Dist: keras
Requires-Dist: lazy-loader
